_pyoomph.cpython-39-darwin.so
_pyoomph-stubs/__init__.pyi
_pyoomph-stubs/py.typed
pyoomph-0.1.7.dist-info/RECORD
pyoomph-0.1.7.dist-info/WHEEL
pyoomph-0.1.7.dist-info/top_level.txt
pyoomph-0.1.7.dist-info/METADATA
pyoomph-0.1.7.dist-info/licenses/COPYING
pyoomph/_version.py
pyoomph/__init__.py
pyoomph/NO_MPI
pyoomph/py.typed
pyoomph/__main__.py
pyoomph/materials/generic.py
pyoomph/materials/activity.py
pyoomph/materials/__init__.py
pyoomph/materials/default_materials.py
pyoomph/materials/mass_transfer.py
pyoomph/materials/surfactant_isotherms.py
pyoomph/materials/csv_data/__init__.py
pyoomph/materials/csv_data/surftens_water_12hexanediol_ring.csv
pyoomph/materials/csv_data/smooth.py
pyoomph/materials/csv_data/surftens_water_12hexanediol_pendant.csv
pyoomph/materials/UNIFAC/__init__.py
pyoomph/materials/UNIFAC/aiomfac.py
pyoomph/materials/UNIFAC/original.py
pyoomph/materials/UNIFAC/dortmund.py
pyoomph/jitbridge/jitbridge.h
pyoomph/jitbridge/jitbridge_hang.h
pyoomph/jitbridge/__init__.py
pyoomph/jitbridge/jitbridge_nohang.h
pyoomph/equations/potential_flow.py
pyoomph/equations/navier_stokes.py
pyoomph/equations/advection_diffusion.py
pyoomph/equations/solid.py
pyoomph/equations/poisson.py
pyoomph/equations/lubrication.py
pyoomph/equations/topological_changes.py
pyoomph/equations/cahn_hilliard.py
pyoomph/equations/tracers.py
pyoomph/equations/generic.py
pyoomph/equations/__init__.py
pyoomph/equations/low_order_NSCH.py
pyoomph/equations/kuramoto_sivashinsky.py
pyoomph/equations/multi_component.py
pyoomph/equations/SUPG.py
pyoomph/equations/ode.py
pyoomph/equations/helmholtz.py
pyoomph/equations/contact_angle.py
pyoomph/equations/ALE.py
pyoomph/equations/stokes_stream_func.py
pyoomph/equations/harmonic_oscillator.py
pyoomph/equations/NSCH.py
pyoomph/equations/darcy.py
pyoomph/typings/__init__.py
pyoomph/output/plotting.py
pyoomph/output/generic.py
pyoomph/output/__init__.py
pyoomph/output/plotting3d.py
pyoomph/output/meshio.py
pyoomph/output/states.py
pyoomph/output/latex.py
pyoomph/solvers/precice_adapter.py
pyoomph/solvers/load_solver_from_cmd_line.py
pyoomph/solvers/generic.py
