Metadata-Version: 2.4
Name: pyoomph
Version: 0.1.7
Summary: pyoomph - a multi-physics finite element framework based on oomph-lib and GiNaC
Author-email: Christian Diddens <c.diddens@utwente.nl>, Duarte Rocha <d.rocha@utwente.nl>
License: GNU GENERAL PUBLIC LICENSE Version 3
Project-URL: homepage, https://pyoomph.github.io
Project-URL: documentation, https://pyoomph.readthedocs.io/en/latest/index.html
Project-URL: source, https://github.com/pyoomph/pyoomph
Project-URL: download, https://pypi.org/project/pyoomph/
Project-URL: tracker, https://github.com/pyoomph/pyoomph/issues
Classifier: Development Status :: 3 - Alpha
Classifier: Intended Audience :: Science/Research
Classifier: Natural Language :: English
Classifier: License :: OSI Approved :: GNU General Public License v3 (GPLv3)
Classifier: Operating System :: POSIX :: Linux
Classifier: Operating System :: Unix
Classifier: Operating System :: MacOS :: MacOS X
Classifier: Operating System :: Microsoft :: Windows :: Windows 10
Classifier: Operating System :: Microsoft :: Windows :: Windows 11
Classifier: Programming Language :: Python
Classifier: Programming Language :: Python :: 3
Classifier: Programming Language :: Python :: 3.9
Classifier: Programming Language :: Python :: 3.10
Classifier: Programming Language :: Python :: 3.11
Classifier: Programming Language :: Python :: 3.12
Classifier: Programming Language :: Python :: 3.13
Classifier: Topic :: Scientific/Engineering
Classifier: Topic :: Scientific/Engineering :: Mathematics
Classifier: Topic :: Scientific/Engineering :: Physics
Requires-Python: >=3.9
License-File: COPYING
Requires-Dist: meshio>=5.3.4
Requires-Dist: pygmsh>=7.1.17
Requires-Dist: numpy>=1.24.4
Requires-Dist: scipy>=1.10.1
Requires-Dist: matplotlib>=3.7.5
Requires-Dist: more_itertools>=10.2.0
Requires-Dist: tccbox>=2024.3.18
Requires-Dist: setuptools>=69.5.1
Requires-Dist: mkl>=2021.4.0; sys_platform != "darwin"
Requires-Dist: mkl==2021.4.0; sys_platform == "darwin"
Dynamic: license-file
